{
  "accountId": "string",
  "arn": "string",
  "availabilityZone": "string",
  "awsRegion": "string",
  "configuration.ApplicationId": "string",
  "configuration.Arn": "string",
  "configuration.Dimensions.Behavior.Recency.Duration": "string",
  "configuration.Dimensions.Behavior.Recency.RecencyType": "string",
  "configuration.Dimensions.Demographic.AppVersion.DimensionType": "string",
  "configuration.Dimensions.Demographic.AppVersion.Values": "string",
  "configuration.Dimensions.Demographic.Channel.DimensionType": "string",
  "configuration.Dimensions.Demographic.Channel.Values": "string",
  "configuration.Dimensions.Demographic.DeviceType.DimensionType": "string",
  "configuration.Dimensions.Demographic.DeviceType.Values": "string",
  "configuration.Dimensions.Demographic.Make.DimensionType": "string",
  "configuration.Dimensions.Demographic.Make.Values": "string",
  "configuration.Dimensions.Demographic.Model.DimensionType": "string",
  "configuration.Dimensions.Demographic.Model.Values": "string",
  "configuration.Dimensions.Demographic.Platform.DimensionType": "string",
  "configuration.Dimensions.Demographic.Platform.Values": "string",
  "configuration.Dimensions.Location.Country.DimensionType": "string",
  "configuration.Dimensions.Location.Country.Values": "string",
  "configuration.Dimensions.Location.GPSPoint.Coordinates.Latitude": "float",
  "configuration.Dimensions.Location.GPSPoint.Coordinates.Longitude": "float",
  "configuration.Dimensions.Location.GPSPoint.RangeInKilometers": "float",
  "configuration.Name": "string",
  "configuration.SegmentGroups.Groups.Dimensions.Behavior.Recency.Duration": "string",
  "configuration.SegmentGroups.Groups.Dimensions.Behavior.Recency.RecencyType": "string",
  "configuration.SegmentGroups.Groups.Dimensions.Demographic.AppVersion.DimensionType": "string",
  "configuration.SegmentGroups.Groups.Dimensions.Demographic.AppVersion.Values": "string",
  "configuration.SegmentGroups.Groups.Dimensions.Demographic.Channel.DimensionType": "string",
  "configuration.SegmentGroups.Groups.Dimensions.Demographic.Channel.Values": "string",
  "configuration.SegmentGroups.Groups.Dimensions.Demographic.DeviceType.DimensionType": "string",
  "configuration.SegmentGroups.Groups.Dimensions.Demographic.DeviceType.Values": "string",
  "configuration.SegmentGroups.Groups.Dimensions.Demographic.Make.DimensionType": "string",
  "configuration.SegmentGroups.Groups.Dimensions.Demographic.Make.Values": "string",
  "configuration.SegmentGroups.Groups.Dimensions.Demographic.Model.DimensionType": "string",
  "configuration.SegmentGroups.Groups.Dimensions.Demographic.Model.Values": "string",
  "configuration.SegmentGroups.Groups.Dimensions.Demographic.Platform.DimensionType": "string",
  "configuration.SegmentGroups.Groups.Dimensions.Demographic.Platform.Values": "string",
  "configuration.SegmentGroups.Groups.Dimensions.Location.Country.DimensionType": "string",
  "configuration.SegmentGroups.Groups.Dimensions.Location.Country.Values": "string",
  "configuration.SegmentGroups.Groups.Dimensions.Location.GPSPoint.Coordinates.Latitude": "float",
  "configuration.SegmentGroups.Groups.Dimensions.Location.GPSPoint.Coordinates.Longitude": "float",
  "configuration.SegmentGroups.Groups.Dimensions.Location.GPSPoint.RangeInKilometers": "float",
  "configuration.SegmentGroups.Groups.SourceSegments.Id": "string",
  "configuration.SegmentGroups.Groups.SourceSegments.Version": "integer",
  "configuration.SegmentGroups.Groups.SourceType": "string",
  "configuration.SegmentGroups.Groups.Type": "string",
  "configuration.SegmentGroups.Include": "string",
  "configuration.SegmentId": "string",
  "configurationItemCaptureTime": "string",
  "configurationItemDeliveryTime": "date",
  "configurationItemStatus": "string",
  "configurationStateId": "string",
  "recordingFrequency": "string",
  "relationships.resourceId": "string",
  "relationships.resourceName": "string",
  "relationships.resourceType": "string",
  "resourceCreationTime": "string",
  "resourceId": "string",
  "resourceName": "string",
  "resourceType": "string",
  "tags.key": "string",
  "tags.tag": "string",
  "tags.value": "string",
  "version": "string"
}
